GAFOC/LICENSE
GAFOC/README.md
GAFOC/__init__.py
GAFOC/exceptions.py
GAFOC/archive/__init__.py
GAFOC/archive/archiver.py
GAFOC/archive/extractor.py
GAFOC/core/__init__.py
GAFOC/core/compression.py
GAFOC/core/decompression.py
GAFOC/core/huffman.c
GAFOC/core/huffman.pyx
gafoc-2.6.3.dist-info/METADATA
gafoc-2.6.3.dist-info/WHEEL
gafoc-2.6.3.dist-info/top_level.txt
gafoc-2.6.3.dist-info/RECORD
