Metadata-Version: 2.4
Name: gafoc
Version: 2.6.3
Summary: A high-performance file compression library (requires C compiler).
Author-email: Gafoo <gafarssprts@gmail.com>
Project-URL: Homepage, https://github.com/gafoo173/
Project-URL: Bug Tracker, https://github.com/gafoo173/
Classifier: Development Status :: 4 - Beta
Classifier: Intended Audience :: Developers
Classifier: License :: OSI Approved :: MIT License
Classifier: Operating System :: OS Independent
Classifier: Programming Language :: Python :: 3
Classifier: Programming Language :: Cython
Classifier: Topic :: System :: Archiving :: Compression
Requires-Python: >=3.7
Requires-Dist: lz4
Requires-Dist: zstandard
Requires-Dist: brotli
